watson/__init__.py
watson/validators/__init__.py
watson/validators/abc.py
watson/validators/numeric.py
watson/validators/string.py
watson_validators-1.0.6.dist-info/DESCRIPTION.rst
watson_validators-1.0.6.dist-info/METADATA
watson_validators-1.0.6.dist-info/RECORD
watson_validators-1.0.6.dist-info/WHEEL
watson_validators-1.0.6.dist-info/metadata.json
watson_validators-1.0.6.dist-info/top_level.txt
