Metadata-Version: 2.0
Name: watson-validators
Version: 1.0.6
Summary: Validate and verify arbitrary values.
Home-page: http://github.com/watsonpy/watson-validators
Author: Simon Coulton
Author-email: simon@bespohk.com
License: Copyright (c) 2012-2016 Bespohk, and is maintained by multiple
Provides-Extra: test
Requires-Dist: coverage; extra == 'test'
Requires-Dist: coveralls; extra == 'test'
Requires-Dist: pytest; extra == 'test'
Requires-Dist: pytest-cov; extra == 'test'
